LICENSE
README.md
setup.py
latentplot.egg-info/PKG-INFO
latentplot.egg-info/SOURCES.txt
latentplot.egg-info/dependency_links.txt
latentplot.egg-info/requires.txt
latentplot.egg-info/top_level.txt
src/__init__.py
src/latentplotter.py
test/test_latentplot.py