Metadata-Version: 2.1
Name: latentplot
Version: 0.0.2
Summary: Python module to produce an image plot of latent spaces.
Home-page: https://github.com/luiscarlosgph/latentplot
Author: Luis C. Garcia-Peraza Herrera
Author-email: luiscarlos.gph@gmail.com
License: MIT License
Platform: UNKNOWN
License-File: LICENSE
